timeless_memory/__init__.py
timeless_memory/cli.py
timeless_memory/mcp_server.py
timeless_memory/core/__init__.py
timeless_memory/core/entity_manager.py
timeless_memory/core/index_manager.py
timeless_memory/core/manager_factory.py
timeless_memory/core/memory_manager.py
timeless_memory/core/query_utils.py
timeless_memory/core/relation_manager.py
timeless_memory/core/resolver.py
timeless_memory/core/retrieval_engine.py
timeless_memory/integrations/__init__.py
timeless_memory/integrations/google_chat/__init__.py
timeless_memory/integrations/google_chat/auth.py
timeless_memory/integrations/google_chat/chat_manager.py
timeless_memory/integrations/google_chat/converter.py
timeless_memory/integrations/google_chat/downloader.py
timeless_memory/integrations/google_chat/parallel_converter.py
timeless_memory/interfaces/__init__.py
timeless_memory/interfaces/base_command.py
timeless_memory/interfaces/command_registry.py
timeless_memory/interfaces/commands.py
timeless_memory/interfaces/formatters.py
timeless_memory_mcp-0.1.6.dist-info/METADATA
timeless_memory_mcp-0.1.6.dist-info/WHEEL
timeless_memory_mcp-0.1.6.dist-info/entry_points.txt
timeless_memory_mcp-0.1.6.dist-info/RECORD
