Metadata-Version: 2.4
Name: timeless-memory-mcp
Version: 0.1.6
Summary: Timeless Memory - 個人記憶系統 MCP Server（SQLite FTS5 全文檢索）
Project-URL: Homepage, https://github.com/chenwei/timeless-memory-mcp
Project-URL: Repository, https://github.com/chenwei/timeless-memory-mcp
Project-URL: Issues, https://github.com/chenwei/timeless-memory-mcp/issues
Author: chenwei
License-Expression: MIT
Keywords: ai,fts5,google-chat,knowledge-management,mcp,memory
Classifier: Development Status :: 3 - Alpha
Classifier: Intended Audience :: Developers
Classifier: License :: OSI Approved :: MIT License
Classifier: Programming Language :: Python :: 3
Classifier: Programming Language :: Python :: 3.10
Classifier: Programming Language :: Python :: 3.11
Classifier: Programming Language :: Python :: 3.12
Classifier: Programming Language :: Python :: 3.13
Requires-Python: >=3.10
Requires-Dist: google-api-python-client>=2.0
Requires-Dist: google-auth-oauthlib>=1.0
Requires-Dist: google-auth>=2.0
Requires-Dist: mcp>=1.0.0
Requires-Dist: pydantic>=2.0
Requires-Dist: python-dotenv>=1.0.0
Requires-Dist: pyyaml>=6.0
Provides-Extra: dev
Requires-Dist: pytest-asyncio>=0.23; extra == 'dev'
Requires-Dist: pytest>=7.0; extra == 'dev'
